{
  "StepModels": [
    {
      "$type": "WholesomeDungeonCrawler.Models.RegroupModel, WholesomeDungeonCrawler",
      "RegroupSpot": {
        "X": 260.2484,
        "Y": -27.70093,
        "Z": -2.55924,
        "Type": "None",
        "Action": ""
      },
      "Name": "Regroup at the entrance",
      "CompleteCondition": {
        "ConditionType": 0,
        "ConditionTimer": null,
        "GetTimerTimeLeft": 0.0,
        "TimerTimeInSeconds": 0,
        "HaveItemId": 0,
        "HaveItemMustReturnTrue": true,
        "CanGossipMobId": 0,
        "CanGossipMustReturnTrue": true,
        "InitialFlags": 0,
        "FlagsChangedGameObjectId": 0,
        "DeadMobId": 0,
        "MobDeadMustReturnTrue": true,
        "MobAtPositionId": 0,
        "MobAtPositionVector": null,
        "MobAtPositionMustReturnTrue": true,
        "LOSPositionVectorFrom": null,
        "LOSPositionVectorTo": null,
        "LOSMustReturnTrue": true,
        "MobAttackableEntry": 0,
        "MobAttackableMustReturnTrue": false,
        "MobAttackableSkipIfAbsent": false
      },
      "StepFaction": 0,
      "HasCompleteCondition": false
    },
    {
      "$type": "WholesomeDungeonCrawler.Models.MoveAlongPathModel, WholesomeDungeonCrawler",
      "Path": [
        {
          "X": 267.24588,
          "Y": -27.887722,
          "Z": -2.55923963,
          "Type": "None",
          "Action": ""
        },
        {
          "X": 276.7625,
          "Y": -28.141758,
          "Z": -2.55923963,
          "Type": "None",
          "Action": ""
        },
        {
          "X": 287.727722,
          "Y": -28.8062763,
          "Z": -3.88694024,
          "Type": "None",
          "Action": ""
        },
        {
          "X": 295.94754,
          "Y": -21.1772652,
          "Z": -3.62378,
          "Type": "None",
          "Action": ""
        },
        {
          "X": 295.712372,
          "Y": -8.947422,
          "Z": -3.88573956,
          "Type": "None",
          "Action": ""
        },
        {
          "X": 294.202118,
          "Y": 5.6222167,
          "Z": -3.88573956,
          "Type": "None",
          "Action": ""
        },
        {
          "X": 291.83847,
          "Y": 14.5740757,
          "Z": -3.8928237,
          "Type": "None",
          "Action": ""
        },
        {
          "X": 289.571747,
          "Y": 23.2380428,
          "Z": -3.920471,
          "Type": "None",
          "Action": ""
        },
        {
          "X": 287.6324,
          "Y": 32.1959419,
          "Z": -3.893569,
          "Type": "None",
          "Action": ""
        },
        {
          "X": 294.875366,
          "Y": 37.481926,
          "Z": -3.95870829,
          "Type": "None",
          "Action": ""
        },
        {
          "X": 301.562134,
          "Y": 32.2158928,
          "Z": -3.938946,
          "Type": "None",
          "Action": ""
        },
        {
          "X": 303.515472,
          "Y": 23.9824047,
          "Z": -3.913447,
          "Type": "None",
          "Action": ""
        },
        {
          "X": 305.444336,
          "Y": 15.6343393,
          "Z": -3.88813972,
          "Type": "None",
          "Action": ""
        },
        {
          "X": 308.1375,
          "Y": 7.710231,
          "Z": -3.88623548,
          "Type": "None",
          "Action": ""
        },
        {
          "X": 316.168823,
          "Y": 6.352814,
          "Z": -6.56639433,
          "Type": "None",
          "Action": ""
        },
        {
          "X": 323.314331,
          "Y": 6.20741844,
          "Z": -11.2575178,
          "Type": "None",
          "Action": ""
        },
        {
          "X": 330.44455,
          "Y": 6.0708127,
          "Z": -15.9385509,
          "Type": "None",
          "Action": ""
        },
        {
          "X": 337.5739,
          "Y": 5.650243,
          "Z": -20.6191368,
          "Type": "None",
          "Action": ""
        },
        {
          "X": 344.727631,
          "Y": 5.690114,
          "Z": -24.2805424,
          "Type": "None",
          "Action": ""
        },
        {
          "X": 352.2872,
          "Y": 8.798056,
          "Z": -24.5407619,
          "Type": "None",
          "Action": ""
        },
        {
          "X": 357.0663,
          "Y": 18.6605053,
          "Z": -25.4524937,
          "Type": "None",
          "Action": ""
        },
        {
          "X": 358.819031,
          "Y": 31.2702522,
          "Z": -24.8843956,
          "Type": "None",
          "Action": ""
        },
        {
          "X": 369.017822,
          "Y": 39.8524437,
          "Z": -24.5028076,
          "Type": "None",
          "Action": ""
        },
        {
          "X": 377.541656,
          "Y": 45.6554451,
          "Z": -24.07124,
          "Type": "None",
          "Action": ""
        },
        {
          "X": 384.570435,
          "Y": 50.49683,
          "Z": -23.70935,
          "Type": "None",
          "Action": ""
        },
        {
          "X": 396.643768,
          "Y": 58.38102,
          "Z": -23.4987164,
          "Type": "None",
          "Action": ""
        },
        {
          "X": 408.653076,
          "Y": 65.4036255,
          "Z": -23.4138126,
          "Type": "None",
          "Action": ""
        },
        {
          "X": 421.3714,
          "Y": 71.8150558,
          "Z": -23.4848137,
          "Type": "None",
          "Action": ""
        },
        {
          "X": 428.952332,
          "Y": 67.06759,
          "Z": -23.2455139,
          "Type": "None",
          "Action": ""
        },
        {
          "X": 423.753357,
          "Y": 59.34403,
          "Z": -23.2433815,
          "Type": "None",
          "Action": ""
        },
        {
          "X": 411.326935,
          "Y": 52.52389,
          "Z": -23.3694553,
          "Type": "None",
          "Action": ""
        },
        {
          "X": 407.0358,
          "Y": 43.56269,
          "Z": -24.5041218,
          "Type": "None",
          "Action": ""
        },
        {
          "X": 406.2046,
          "Y": 34.04391,
          "Z": -25.26313,
          "Type": "None",
          "Action": ""
        },
        {
          "X": 405.3785,
          "Y": 24.7003937,
          "Z": -25.5156918,
          "Type": "None",
          "Action": ""
        },
        {
          "X": 403.593536,
          "Y": 10.5563021,
          "Z": -25.2276878,
          "Type": "None",
          "Action": ""
        },
        {
          "X": 402.181274,
          "Y": -0.1284282,
          "Z": -24.94455,
          "Type": "None",
          "Action": ""
        }
      ],
      "IgnoreFightsDuringPath": false,
      "Name": "Boss 1 - Guard Mol'dar",
      "CompleteCondition": {
        "ConditionType": 0,
        "ConditionTimer": null,
        "GetTimerTimeLeft": 0.0,
        "TimerTimeInSeconds": 0,
        "HaveItemId": 0,
        "HaveItemMustReturnTrue": true,
        "CanGossipMobId": 0,
        "CanGossipMustReturnTrue": true,
        "InitialFlags": 0,
        "FlagsChangedGameObjectId": 0,
        "DeadMobId": 0,
        "MobDeadMustReturnTrue": true,
        "MobAtPositionId": 0,
        "MobAtPositionVector": null,
        "MobAtPositionMustReturnTrue": true,
        "LOSPositionVectorFrom": null,
        "LOSPositionVectorTo": null,
        "LOSMustReturnTrue": true,
        "MobAttackableEntry": 0,
        "MobAttackableMustReturnTrue": false,
        "MobAttackableSkipIfAbsent": false
      },
      "StepFaction": 0,
      "HasCompleteCondition": false
    },
    {
      "$type": "WholesomeDungeonCrawler.Models.MoveAlongPathModel, WholesomeDungeonCrawler",
      "Path": [
        {
          "X": 415.505585,
          "Y": -0.142570853,
          "Z": -24.5278,
          "Type": "None",
          "Action": ""
        },
        {
          "X": 423.667725,
          "Y": 0.5322188,
          "Z": -24.2620163,
          "Type": "None",
          "Action": ""
        },
        {
          "X": 434.94635,
          "Y": 1.709293,
          "Z": -17.5976925,
          "Type": "None",
          "Action": ""
        },
        {
          "X": 445.1546,
          "Y": 1.92048371,
          "Z": -10.8963022,
          "Type": "None",
          "Action": ""
        },
        {
          "X": 457.361542,
          "Y": 10.43698,
          "Z": -3.88902831,
          "Type": "None",
          "Action": ""
        },
        {
          "X": 464.455872,
          "Y": 19.0129452,
          "Z": -3.89910531,
          "Type": "None",
          "Action": ""
        },
        {
          "X": 466.755463,
          "Y": 29.9028,
          "Z": -3.892937,
          "Type": "None",
          "Action": ""
        },
        {
          "X": 468.3177,
          "Y": 38.2986832,
          "Z": -3.88712573,
          "Type": "None",
          "Action": ""
        },
        {
          "X": 469.7819,
          "Y": 46.49899,
          "Z": -3.88683319,
          "Type": "None",
          "Action": ""
        },
        {
          "X": 471.529083,
          "Y": 56.28423,
          "Z": -3.88683319,
          "Type": "None",
          "Action": ""
        },
        {
          "X": 473.5053,
          "Y": 64.37641,
          "Z": -3.88683319,
          "Type": "None",
          "Action": ""
        },
        {
          "X": 478.558563,
          "Y": 79.47192,
          "Z": -3.88683319,
          "Type": "None",
          "Action": ""
        },
        {
          "X": 482.007751,
          "Y": 87.89291,
          "Z": -3.4531076,
          "Type": "None",
          "Action": ""
        }
      ],
      "IgnoreFightsDuringPath": false,
      "Name": "Boss 2 - Stomper Kreeg",
      "CompleteCondition": {
        "ConditionType": 0,
        "ConditionTimer": null,
        "GetTimerTimeLeft": 0.0,
        "TimerTimeInSeconds": 0,
        "HaveItemId": 0,
        "HaveItemMustReturnTrue": true,
        "CanGossipMobId": 0,
        "CanGossipMustReturnTrue": true,
        "InitialFlags": 0,
        "FlagsChangedGameObjectId": 0,
        "DeadMobId": 0,
        "MobDeadMustReturnTrue": true,
        "MobAtPositionId": 0,
        "MobAtPositionVector": null,
        "MobAtPositionMustReturnTrue": true,
        "LOSPositionVectorFrom": null,
        "LOSPositionVectorTo": null,
        "LOSMustReturnTrue": true,
        "MobAttackableEntry": 0,
        "MobAttackableMustReturnTrue": false,
        "MobAttackableSkipIfAbsent": false
      },
      "StepFaction": 0,
      "HasCompleteCondition": false
    },
    {
      "$type": "WholesomeDungeonCrawler.Models.RegroupModel, WholesomeDungeonCrawler",
      "RegroupSpot": {
        "X": 479.6427,
        "Y": 100.2548,
        "Z": -3.886342,
        "Type": "None",
        "Action": ""
      },
      "Name": "Regroup after 2 boss",
      "CompleteCondition": {
        "ConditionType": 0,
        "ConditionTimer": null,
        "GetTimerTimeLeft": 0.0,
        "TimerTimeInSeconds": 0,
        "HaveItemId": 0,
        "HaveItemMustReturnTrue": true,
        "CanGossipMobId": 0,
        "CanGossipMustReturnTrue": true,
        "InitialFlags": 0,
        "FlagsChangedGameObjectId": 0,
        "DeadMobId": 0,
        "MobDeadMustReturnTrue": true,
        "MobAtPositionId": 0,
        "MobAtPositionVector": null,
        "MobAtPositionMustReturnTrue": true,
        "LOSPositionVectorFrom": null,
        "LOSPositionVectorTo": null,
        "LOSMustReturnTrue": true,
        "MobAttackableEntry": 0,
        "MobAttackableMustReturnTrue": false,
        "MobAttackableSkipIfAbsent": false
      },
      "StepFaction": 0,
      "HasCompleteCondition": false
    },
    {
      "$type": "WholesomeDungeonCrawler.Models.MoveAlongPathModel, WholesomeDungeonCrawler",
      "Path": [
        {
          "X": 472.558929,
          "Y": 111.0162,
          "Z": -3.886887,
          "Type": "None",
          "Action": ""
        },
        {
          "X": 466.411316,
          "Y": 117.72554,
          "Z": -3.886887,
          "Type": "None",
          "Action": ""
        },
        {
          "X": 458.8859,
          "Y": 129.691483,
          "Z": -2.80583239,
          "Type": "None",
          "Action": ""
        },
        {
          "X": 454.474548,
          "Y": 137.044708,
          "Z": -2.583436,
          "Type": "None",
          "Action": ""
        },
        {
          "X": 447.574158,
          "Y": 149.385681,
          "Z": 2.61186838,
          "Type": "None",
          "Action": ""
        },
        {
          "X": 440.635864,
          "Y": 153.430954,
          "Z": 3.86291933,
          "Type": "None",
          "Action": ""
        },
        {
          "X": 432.85672,
          "Y": 155.5012,
          "Z": 3.864825,
          "Type": "None",
          "Action": ""
        },
        {
          "X": 423.381683,
          "Y": 165.912415,
          "Z": 2.85292387,
          "Type": "None",
          "Action": ""
        },
        {
          "X": 417.382538,
          "Y": 174.13147,
          "Z": 2.85292387,
          "Type": "None",
          "Action": ""
        },
        {
          "X": 409.54068,
          "Y": 165.362335,
          "Z": 2.85293841,
          "Type": "None",
          "Action": ""
        },
        {
          "X": 402.6217,
          "Y": 159.156174,
          "Z": 3.5466578,
          "Type": "None",
          "Action": ""
        },
        {
          "X": 395.144928,
          "Y": 152.192245,
          "Z": 3.821842,
          "Type": "None",
          "Action": ""
        },
        {
          "X": 386.930573,
          "Y": 149.318283,
          "Z": 2.582915,
          "Type": "None",
          "Action": ""
        },
        {
          "X": 392.521179,
          "Y": 115.526443,
          "Z": -3.886866,
          "Type": "None",
          "Action": ""
        }
      ],
      "IgnoreFightsDuringPath": false,
      "Name": "Move close to Boss 3 platform",
      "CompleteCondition": {
        "ConditionType": 0,
        "ConditionTimer": null,
        "GetTimerTimeLeft": 0.0,
        "TimerTimeInSeconds": 0,
        "HaveItemId": 0,
        "HaveItemMustReturnTrue": true,
        "CanGossipMobId": 0,
        "CanGossipMustReturnTrue": true,
        "InitialFlags": 0,
        "FlagsChangedGameObjectId": 0,
        "DeadMobId": 0,
        "MobDeadMustReturnTrue": true,
        "MobAtPositionId": 0,
        "MobAtPositionVector": null,
        "MobAtPositionMustReturnTrue": true,
        "LOSPositionVectorFrom": null,
        "LOSPositionVectorTo": null,
        "LOSMustReturnTrue": true,
        "MobAttackableEntry": 0,
        "MobAttackableMustReturnTrue": false,
        "MobAttackableSkipIfAbsent": false
      },
      "StepFaction": 0,
      "HasCompleteCondition": false
    },
    {
      "$type": "WholesomeDungeonCrawler.Models.PullToSafeSpotModel, WholesomeDungeonCrawler",
      "SafeSpotPosition": {
        "X": 386.1337,
        "Y": 181.6867,
        "Z": 5.233006,
        "Type": "None",
        "Action": ""
      },
      "SafeSpotRadius": 20,
      "ZoneToClearPosition": {
        "X": 384.4965,
        "Y": 224.5937,
        "Z": 11.20639,
        "Type": "None",
        "Action": ""
      },
      "ZoneToClearRadius": 60,
      "ZoneToClearZLimit": 15,
      "Name": "Kill some trash from the platform",
      "CompleteCondition": {
        "ConditionType": 0,
        "ConditionTimer": null,
        "GetTimerTimeLeft": 0.0,
        "TimerTimeInSeconds": 0,
        "HaveItemId": 0,
        "HaveItemMustReturnTrue": true,
        "CanGossipMobId": 0,
        "CanGossipMustReturnTrue": true,
        "InitialFlags": 0,
        "FlagsChangedGameObjectId": 0,
        "DeadMobId": 0,
        "MobDeadMustReturnTrue": true,
        "MobAtPositionId": 0,
        "MobAtPositionVector": null,
        "MobAtPositionMustReturnTrue": true,
        "LOSPositionVectorFrom": null,
        "LOSPositionVectorTo": null,
        "LOSMustReturnTrue": true,
        "MobAttackableEntry": 0,
        "MobAttackableMustReturnTrue": false,
        "MobAttackableSkipIfAbsent": false
      },
      "StepFaction": 0,
      "HasCompleteCondition": false
    },
    {
      "$type": "WholesomeDungeonCrawler.Models.MoveAlongPathModel, WholesomeDungeonCrawler",
      "Path": [
        {
          "X": 386.821777,
          "Y": 187.462143,
          "Z": 7.68387842,
          "Type": "None",
          "Action": ""
        },
        {
          "X": 386.32666,
          "Y": 201.215027,
          "Z": 11.2174206,
          "Type": "None",
          "Action": ""
        },
        {
          "X": 394.117767,
          "Y": 210.938736,
          "Z": 11.2079525,
          "Type": "None",
          "Action": ""
        },
        {
          "X": 402.4341,
          "Y": 221.317978,
          "Z": 11.2040405,
          "Type": "None",
          "Action": ""
        },
        {
          "X": 412.4137,
          "Y": 233.773041,
          "Z": 11.20416,
          "Type": "None",
          "Action": ""
        },
        {
          "X": 419.494537,
          "Y": 240.135071,
          "Z": 11.20416,
          "Type": "None",
          "Action": ""
        },
        {
          "X": 430.240173,
          "Y": 243.532761,
          "Z": 11.20416,
          "Type": "None",
          "Action": ""
        },
        {
          "X": 439.601166,
          "Y": 247.8923,
          "Z": 11.2060966,
          "Type": "None",
          "Action": ""
        },
        {
          "X": 442.4202,
          "Y": 256.345978,
          "Z": 11.2081118,
          "Type": "None",
          "Action": ""
        },
        {
          "X": 442.02124,
          "Y": 271.8794,
          "Z": 11.2089233,
          "Type": "None",
          "Action": ""
        },
        {
          "X": 441.879944,
          "Y": 280.9083,
          "Z": 11.2089233,
          "Type": "None",
          "Action": ""
        },
        {
          "X": 440.482849,
          "Y": 293.57016,
          "Z": 11.2043467,
          "Type": "None",
          "Action": ""
        },
        {
          "X": 433.430359,
          "Y": 302.21225,
          "Z": 11.2029266,
          "Type": "None",
          "Action": ""
        },
        {
          "X": 424.4725,
          "Y": 304.170349,
          "Z": 11.20753,
          "Type": "None",
          "Action": ""
        },
        {
          "X": 415.823242,
          "Y": 304.899231,
          "Z": 11.2093954,
          "Type": "None",
          "Action": ""
        },
        {
          "X": 406.2418,
          "Y": 305.0747,
          "Z": 11.2095871,
          "Type": "None",
          "Action": ""
        },
        {
          "X": 387.252441,
          "Y": 306.193939,
          "Z": 11.2110376,
          "Type": "None",
          "Action": ""
        },
        {
          "X": 376.077,
          "Y": 306.927765,
          "Z": 11.213542,
          "Type": "None",
          "Action": ""
        },
        {
          "X": 367.46814,
          "Y": 306.937073,
          "Z": 11.213542,
          "Type": "None",
          "Action": ""
        },
        {
          "X": 355.859619,
          "Y": 306.499847,
          "Z": 11.213542,
          "Type": "None",
          "Action": ""
        },
        {
          "X": 346.0593,
          "Y": 302.190643,
          "Z": 11.2105713,
          "Type": "None",
          "Action": ""
        },
        {
          "X": 335.620483,
          "Y": 295.543457,
          "Z": 11.2030172,
          "Type": "None",
          "Action": ""
        },
        {
          "X": 327.448425,
          "Y": 284.5087,
          "Z": 11.2085323,
          "Type": "None",
          "Action": ""
        },
        {
          "X": 325.8683,
          "Y": 274.0001,
          "Z": 11.2099342,
          "Type": "None",
          "Action": ""
        },
        {
          "X": 321.074463,
          "Y": 256.8317,
          "Z": 11.2140961,
          "Type": "None",
          "Action": ""
        },
        {
          "X": 363.7167,
          "Y": 281.078979,
          "Z": 11.2064495,
          "Type": "None",
          "Action": ""
        }
      ],
      "IgnoreFightsDuringPath": false,
      "Name": "Boss 3 - Guard Fengus",
      "CompleteCondition": {
        "ConditionType": 0,
        "ConditionTimer": null,
        "GetTimerTimeLeft": 0.0,
        "TimerTimeInSeconds": 0,
        "HaveItemId": 0,
        "HaveItemMustReturnTrue": true,
        "CanGossipMobId": 0,
        "CanGossipMustReturnTrue": true,
        "InitialFlags": 0,
        "FlagsChangedGameObjectId": 0,
        "DeadMobId": 0,
        "MobDeadMustReturnTrue": true,
        "MobAtPositionId": 0,
        "MobAtPositionVector": null,
        "MobAtPositionMustReturnTrue": true,
        "LOSPositionVectorFrom": null,
        "LOSPositionVectorTo": null,
        "LOSMustReturnTrue": true,
        "MobAttackableEntry": 0,
        "MobAttackableMustReturnTrue": false,
        "MobAttackableSkipIfAbsent": false
      },
      "StepFaction": 0,
      "HasCompleteCondition": false
    },
    {
      "$type": "WholesomeDungeonCrawler.Models.DefendSpotModel, WholesomeDungeonCrawler",
      "DefendPosition": {
        "X": 363.7167,
        "Y": 281.079,
        "Z": 11.20645,
        "Type": "None",
        "Action": ""
      },
      "Timer": 0,
      "DefendSpotRadius": 60,
      "DefendSpotZLimit": 5,
      "ResetTimerOnCombat": false,
      "Name": "Wait for boss 3 if he's patrolling",
      "CompleteCondition": {
        "ConditionType": 4,
        "ConditionTimer": null,
        "GetTimerTimeLeft": 0.0,
        "TimerTimeInSeconds": 0,
        "HaveItemId": 0,
        "HaveItemMustReturnTrue": true,
        "CanGossipMobId": 0,
        "CanGossipMustReturnTrue": true,
        "InitialFlags": 0,
        "FlagsChangedGameObjectId": 0,
        "DeadMobId": 14321,
        "MobDeadMustReturnTrue": true,
        "MobAtPositionId": 0,
        "MobAtPositionVector": null,
        "MobAtPositionMustReturnTrue": true,
        "LOSPositionVectorFrom": null,
        "LOSPositionVectorTo": null,
        "LOSMustReturnTrue": true,
        "MobAttackableEntry": 0,
        "MobAttackableMustReturnTrue": false,
        "MobAttackableSkipIfAbsent": false
      },
      "StepFaction": 0,
      "HasCompleteCondition": true
    },
    {
      "$type": "WholesomeDungeonCrawler.Models.InteractWithModel, WholesomeDungeonCrawler",
      "ObjectId": "179516",
      "ExpectedPosition": {
        "X": 385.031,
        "Y": 260.257,
        "Z": 11.4396,
        "Type": "None",
        "Action": ""
      },
      "InteractDistance": 3,
      "SkipIfNotFound": true,
      "Name": "Open Fengus chest",
      "CompleteCondition": {
        "ConditionType": 3,
        "ConditionTimer": null,
        "GetTimerTimeLeft": 0.0,
        "TimerTimeInSeconds": 0,
        "HaveItemId": 18266,
        "HaveItemMustReturnTrue": true,
        "CanGossipMobId": 0,
        "CanGossipMustReturnTrue": true,
        "InitialFlags": 0,
        "FlagsChangedGameObjectId": 0,
        "DeadMobId": 0,
        "MobDeadMustReturnTrue": true,
        "MobAtPositionId": 0,
        "MobAtPositionVector": null,
        "MobAtPositionMustReturnTrue": true,
        "LOSPositionVectorFrom": null,
        "LOSPositionVectorTo": null,
        "LOSMustReturnTrue": true,
        "MobAttackableEntry": 0,
        "MobAttackableMustReturnTrue": false,
        "MobAttackableSkipIfAbsent": false
      },
      "StepFaction": 0,
      "HasCompleteCondition": true
    },
    {
      "$type": "WholesomeDungeonCrawler.Models.MoveAlongPathModel, WholesomeDungeonCrawler",
      "Path": [
        {
          "X": 385.1164,
          "Y": 268.0509,
          "Z": 11.4395819,
          "Type": "None",
          "Action": ""
        },
        {
          "X": 384.925323,
          "Y": 280.369415,
          "Z": 12.2345238,
          "Type": "None",
          "Action": ""
        },
        {
          "X": 384.763031,
          "Y": 290.83316,
          "Z": 11.2049961,
          "Type": "None",
          "Action": ""
        },
        {
          "X": 384.749817,
          "Y": 299.441284,
          "Z": 11.206521,
          "Type": "None",
          "Action": ""
        },
        {
          "X": 385.29184,
          "Y": 310.45282,
          "Z": 11.2172146,
          "Type": "None",
          "Action": ""
        },
        {
          "X": 385.603149,
          "Y": 321.718536,
          "Z": 8.848576,
          "Type": "None",
          "Action": ""
        },
        {
          "X": 386.1365,
          "Y": 329.462036,
          "Z": 5.56265736,
          "Type": "None",
          "Action": ""
        },
        {
          "X": 391.6746,
          "Y": 335.815979,
          "Z": 2.8703196,
          "Type": "None",
          "Action": ""
        },
        {
          "X": 398.60907,
          "Y": 340.888916,
          "Z": 2.85374355,
          "Type": "None",
          "Action": ""
        },
        {
          "X": 392.5215,
          "Y": 349.00415,
          "Z": 3.17076,
          "Type": "None",
          "Action": ""
        },
        {
          "X": 387.333527,
          "Y": 359.965576,
          "Z": 1.84377265,
          "Type": "None",
          "Action": ""
        },
        {
          "X": 385.6158,
          "Y": 369.407043,
          "Z": -0.205172539,
          "Type": "None",
          "Action": ""
        }
      ],
      "IgnoreFightsDuringPath": false,
      "Name": "Move to the gate 1",
      "CompleteCondition": {
        "ConditionType": 0,
        "ConditionTimer": null,
        "GetTimerTimeLeft": 0.0,
        "TimerTimeInSeconds": 0,
        "HaveItemId": 0,
        "HaveItemMustReturnTrue": true,
        "CanGossipMobId": 0,
        "CanGossipMustReturnTrue": true,
        "InitialFlags": 0,
        "FlagsChangedGameObjectId": 0,
        "DeadMobId": 0,
        "MobDeadMustReturnTrue": true,
        "MobAtPositionId": 0,
        "MobAtPositionVector": null,
        "MobAtPositionMustReturnTrue": true,
        "LOSPositionVectorFrom": null,
        "LOSPositionVectorTo": null,
        "LOSMustReturnTrue": true,
        "MobAttackableEntry": 0,
        "MobAttackableMustReturnTrue": false,
        "MobAttackableSkipIfAbsent": false
      },
      "StepFaction": 0,
      "HasCompleteCondition": false
    },
    {
      "$type": "WholesomeDungeonCrawler.Models.RegroupModel, WholesomeDungeonCrawler",
      "RegroupSpot": {
        "X": 385.3511,
        "Y": 371.0426,
        "Z": -0.5601197,
        "Type": "None",
        "Action": ""
      },
      "Name": "Regroup before gate 1",
      "CompleteCondition": {
        "ConditionType": 0,
        "ConditionTimer": null,
        "GetTimerTimeLeft": 0.0,
        "TimerTimeInSeconds": 0,
        "HaveItemId": 0,
        "HaveItemMustReturnTrue": true,
        "CanGossipMobId": 0,
        "CanGossipMustReturnTrue": true,
        "InitialFlags": 0,
        "FlagsChangedGameObjectId": 0,
        "DeadMobId": 0,
        "MobDeadMustReturnTrue": true,
        "MobAtPositionId": 0,
        "MobAtPositionVector": null,
        "MobAtPositionMustReturnTrue": true,
        "LOSPositionVectorFrom": null,
        "LOSPositionVectorTo": null,
        "LOSMustReturnTrue": true,
        "MobAttackableEntry": 0,
        "MobAttackableMustReturnTrue": false,
        "MobAttackableSkipIfAbsent": false
      },
      "StepFaction": 0,
      "HasCompleteCondition": false
    },
    {
      "$type": "WholesomeDungeonCrawler.Models.InteractWithModel, WholesomeDungeonCrawler",
      "ObjectId": "177219",
      "ExpectedPosition": {
        "X": 385.327,
        "Y": 374.232,
        "Z": -1.34314,
        "Type": "None",
        "Action": ""
      },
      "InteractDistance": 5,
      "SkipIfNotFound": false,
      "Name": "Open the gate 1",
      "CompleteCondition": {
        "ConditionType": 0,
        "ConditionTimer": null,
        "GetTimerTimeLeft": 0.0,
        "TimerTimeInSeconds": 0,
        "HaveItemId": 0,
        "HaveItemMustReturnTrue": true,
        "CanGossipMobId": 0,
        "CanGossipMustReturnTrue": true,
        "InitialFlags": 0,
        "FlagsChangedGameObjectId": 0,
        "DeadMobId": 0,
        "MobDeadMustReturnTrue": true,
        "MobAtPositionId": 0,
        "MobAtPositionVector": null,
        "MobAtPositionMustReturnTrue": true,
        "LOSPositionVectorFrom": {
          "X": 385.3248,
          "Y": 374.2014,
          "Z": -1.245564,
          "Type": "None",
          "Action": ""
        },
        "LOSPositionVectorTo": {
          "X": 385.2262,
          "Y": 392.5841,
          "Z": -1.676684,
          "Type": "None",
          "Action": ""
        },
        "LOSMustReturnTrue": true,
        "MobAttackableEntry": 0,
        "MobAttackableMustReturnTrue": false,
        "MobAttackableSkipIfAbsent": false
      },
      "StepFaction": 0,
      "HasCompleteCondition": false
    },
    {
      "$type": "WholesomeDungeonCrawler.Models.DefendSpotModel, WholesomeDungeonCrawler",
      "DefendPosition": {
        "X": 385.7524,
        "Y": 367.2835,
        "Z": 0.2556558,
        "Type": "None",
        "Action": ""
      },
      "Timer": 8,
      "DefendSpotRadius": 4,
      "DefendSpotZLimit": 5,
      "ResetTimerOnCombat": false,
      "Name": "Wait for the gate 1 to open",
      "CompleteCondition": {
        "ConditionType": 0,
        "ConditionTimer": null,
        "GetTimerTimeLeft": 0.0,
        "TimerTimeInSeconds": 0,
        "HaveItemId": 0,
        "HaveItemMustReturnTrue": true,
        "CanGossipMobId": 0,
        "CanGossipMustReturnTrue": true,
        "InitialFlags": 0,
        "FlagsChangedGameObjectId": 0,
        "DeadMobId": 0,
        "MobDeadMustReturnTrue": true,
        "MobAtPositionId": 0,
        "MobAtPositionVector": null,
        "MobAtPositionMustReturnTrue": true,
        "LOSPositionVectorFrom": {
          "X": 385.3248,
          "Y": 374.2014,
          "Z": -1.245564,
          "Type": "None",
          "Action": ""
        },
        "LOSPositionVectorTo": {
          "X": 385.2262,
          "Y": 392.5841,
          "Z": -1.676684,
          "Type": "None",
          "Action": ""
        },
        "LOSMustReturnTrue": false,
        "MobAttackableEntry": 0,
        "MobAttackableMustReturnTrue": false,
        "MobAttackableSkipIfAbsent": false
      },
      "StepFaction": 0,
      "HasCompleteCondition": false
    },
    {
      "$type": "WholesomeDungeonCrawler.Models.JumpToStepModel, WholesomeDungeonCrawler",
      "StepToJumpTo": "Leave dungeon",
      "Name": "Check if the gate is open",
      "CompleteCondition": {
        "ConditionType": 6,
        "ConditionTimer": null,
        "GetTimerTimeLeft": 0.0,
        "TimerTimeInSeconds": 0,
        "HaveItemId": 18266,
        "HaveItemMustReturnTrue": false,
        "CanGossipMobId": 0,
        "CanGossipMustReturnTrue": true,
        "InitialFlags": 0,
        "FlagsChangedGameObjectId": 0,
        "DeadMobId": 0,
        "MobDeadMustReturnTrue": true,
        "MobAtPositionId": 0,
        "MobAtPositionVector": null,
        "MobAtPositionMustReturnTrue": true,
        "LOSPositionVectorFrom": {
          "X": 386.0316,
          "Y": 368.8828,
          "Z": -0.09144269,
          "Type": "None",
          "Action": ""
        },
        "LOSPositionVectorTo": {
          "X": 385.8061,
          "Y": 390.6346,
          "Z": -1.676709,
          "Type": "None",
          "Action": ""
        },
        "LOSMustReturnTrue": false,
        "MobAttackableEntry": 0,
        "MobAttackableMustReturnTrue": false,
        "MobAttackableSkipIfAbsent": false
      },
      "StepFaction": 0,
      "HasCompleteCondition": true
    },
    {
      "$type": "WholesomeDungeonCrawler.Models.MoveAlongPathModel, WholesomeDungeonCrawler",
      "Path": [
        {
          "X": 385.056274,
          "Y": 394.399231,
          "Z": -1.67670989,
          "Type": "None",
          "Action": ""
        },
        {
          "X": 385.5712,
          "Y": 406.218018,
          "Z": -1.67670989,
          "Type": "None",
          "Action": ""
        },
        {
          "X": 385.903931,
          "Y": 417.30777,
          "Z": -1.84893835,
          "Type": "None",
          "Action": ""
        },
        {
          "X": 386.9533,
          "Y": 431.372,
          "Z": -4.8201623,
          "Type": "None",
          "Action": ""
        },
        {
          "X": 387.740723,
          "Y": 441.2808,
          "Z": -6.91349649,
          "Type": "None",
          "Action": ""
        },
        {
          "X": 388.0573,
          "Y": 452.107574,
          "Z": -7.23225927,
          "Type": "None",
          "Action": ""
        },
        {
          "X": 385.7358,
          "Y": 465.487671,
          "Z": -7.23225927,
          "Type": "None",
          "Action": ""
        },
        {
          "X": 385.975952,
          "Y": 475.607574,
          "Z": -7.23225927,
          "Type": "None",
          "Action": ""
        },
        {
          "X": 388.41214,
          "Y": 486.2718,
          "Z": -8.0468,
          "Type": "None",
          "Action": ""
        },
        {
          "X": 392.594116,
          "Y": 496.925385,
          "Z": -11.0720434,
          "Type": "None",
          "Action": ""
        },
        {
          "X": 398.647278,
          "Y": 509.6084,
          "Z": -12.7878256,
          "Type": "None",
          "Action": ""
        },
        {
          "X": 406.4648,
          "Y": 521.2363,
          "Z": -13.2679157,
          "Type": "None",
          "Action": ""
        },
        {
          "X": 415.554016,
          "Y": 531.3063,
          "Z": -18.027916,
          "Type": "None",
          "Action": ""
        },
        {
          "X": 426.302063,
          "Y": 541.006958,
          "Z": -18.343277,
          "Type": "None",
          "Action": ""
        },
        {
          "X": 435.579559,
          "Y": 543.0628,
          "Z": -18.5755272,
          "Type": "None",
          "Action": ""
        },
        {
          "X": 449.613464,
          "Y": 543.118347,
          "Z": -22.66448,
          "Type": "None",
          "Action": ""
        },
        {
          "X": 460.373077,
          "Y": 542.518738,
          "Z": -23.8993073,
          "Type": "None",
          "Action": ""
        },
        {
          "X": 469.3285,
          "Y": 542.234863,
          "Z": -25.14909,
          "Type": "None",
          "Action": ""
        },
        {
          "X": 478.789032,
          "Y": 541.177,
          "Z": -25.368578,
          "Type": "None",
          "Action": ""
        },
        {
          "X": 487.720764,
          "Y": 540.12854,
          "Z": -24.58081,
          "Type": "None",
          "Action": ""
        },
        {
          "X": 499.975952,
          "Y": 538.779053,
          "Z": -25.3837948,
          "Type": "None",
          "Action": ""
        },
        {
          "X": 510.9685,
          "Y": 538.1082,
          "Z": -25.3909512,
          "Type": "None",
          "Action": ""
        },
        {
          "X": 520.3724,
          "Y": 539.4987,
          "Z": -25.3967915,
          "Type": "None",
          "Action": ""
        },
        {
          "X": 530.3885,
          "Y": 541.3379,
          "Z": -25.4027176,
          "Type": "None",
          "Action": ""
        },
        {
          "X": 543.233,
          "Y": 539.5934,
          "Z": -25.4027176,
          "Type": "None",
          "Action": ""
        },
        {
          "X": 553.1259,
          "Y": 538.6905,
          "Z": -25.4020081,
          "Type": "None",
          "Action": ""
        },
        {
          "X": 561.36615,
          "Y": 539.0539,
          "Z": -25.4018478,
          "Type": "None",
          "Action": ""
        },
        {
          "X": 570.2656,
          "Y": 543.934631,
          "Z": -25.4007416,
          "Type": "None",
          "Action": ""
        },
        {
          "X": 577.616943,
          "Y": 549.21344,
          "Z": -25.399826,
          "Type": "None",
          "Action": ""
        },
        {
          "X": 579.11,
          "Y": 562.4613,
          "Z": -25.3996162,
          "Type": "None",
          "Action": ""
        },
        {
          "X": 579.4373,
          "Y": 571.1995,
          "Z": -25.3996162,
          "Type": "None",
          "Action": ""
        },
        {
          "X": 579.8811,
          "Y": 585.073,
          "Z": -25.402523,
          "Type": "None",
          "Action": ""
        },
        {
          "X": 570.847656,
          "Y": 586.753967,
          "Z": -25.402523,
          "Type": "None",
          "Action": ""
        },
        {
          "X": 558.973938,
          "Y": 589.4468,
          "Z": -25.402523,
          "Type": "None",
          "Action": ""
        },
        {
          "X": 550.439453,
          "Y": 590.7573,
          "Z": -25.402523,
          "Type": "None",
          "Action": ""
        },
        {
          "X": 541.5236,
          "Y": 590.966736,
          "Z": -25.402523,
          "Type": "None",
          "Action": ""
        },
        {
          "X": 531.114258,
          "Y": 593.3605,
          "Z": -25.402523,
          "Type": "None",
          "Action": ""
        }
      ],
      "IgnoreFightsDuringPath": false,
      "Name": "Boss 4 - Guard Slip'kik",
      "CompleteCondition": {
        "ConditionType": 0,
        "ConditionTimer": null,
        "GetTimerTimeLeft": 0.0,
        "TimerTimeInSeconds": 0,
        "HaveItemId": 0,
        "HaveItemMustReturnTrue": true,
        "CanGossipMobId": 0,
        "CanGossipMustReturnTrue": true,
        "InitialFlags": 0,
        "FlagsChangedGameObjectId": 0,
        "DeadMobId": 0,
        "MobDeadMustReturnTrue": true,
        "MobAtPositionId": 0,
        "MobAtPositionVector": null,
        "MobAtPositionMustReturnTrue": true,
        "LOSPositionVectorFrom": null,
        "LOSPositionVectorTo": null,
        "LOSMustReturnTrue": true,
        "MobAttackableEntry": 0,
        "MobAttackableMustReturnTrue": false,
        "MobAttackableSkipIfAbsent": false
      },
      "StepFaction": 0,
      "HasCompleteCondition": false
    },
    {
      "$type": "WholesomeDungeonCrawler.Models.MoveAlongPathModel, WholesomeDungeonCrawler",
      "Path": [
        {
          "X": 518.5212,
          "Y": 600.2137,
          "Z": -25.4027061,
          "Type": "None",
          "Action": ""
        },
        {
          "X": 510.0958,
          "Y": 602.9383,
          "Z": -25.4027061,
          "Type": "None",
          "Action": ""
        },
        {
          "X": 496.870422,
          "Y": 604.8645,
          "Z": -25.4041,
          "Type": "None",
          "Action": ""
        },
        {
          "X": 487.51886,
          "Y": 603.4156,
          "Z": -25.4041,
          "Type": "None",
          "Action": ""
        },
        {
          "X": 479.044678,
          "Y": 597.7191,
          "Z": -25.4041,
          "Type": "None",
          "Action": ""
        },
        {
          "X": 479.10553,
          "Y": 589.3478,
          "Z": -25.4058189,
          "Type": "None",
          "Action": ""
        },
        {
          "X": 488.363037,
          "Y": 590.3142,
          "Z": -23.0743752,
          "Type": "None",
          "Action": ""
        },
        {
          "X": 500.451721,
          "Y": 590.9332,
          "Z": -17.7028046,
          "Type": "None",
          "Action": ""
        },
        {
          "X": 509.510132,
          "Y": 591.0813,
          "Z": -13.6777658,
          "Type": "None",
          "Action": ""
        },
        {
          "X": 519.4828,
          "Y": 590.87384,
          "Z": -9.246474,
          "Type": "None",
          "Action": ""
        },
        {
          "X": 527.6028,
          "Y": 590.864746,
          "Z": -5.638361,
          "Type": "None",
          "Action": ""
        },
        {
          "X": 538.5772,
          "Y": 589.8988,
          "Z": -4.754745,
          "Type": "None",
          "Action": ""
        },
        {
          "X": 546.3705,
          "Y": 585.7,
          "Z": -4.754745,
          "Type": "None",
          "Action": ""
        },
        {
          "X": 555.2519,
          "Y": 584.5163,
          "Z": -4.754745,
          "Type": "None",
          "Action": ""
        },
        {
          "X": 566.760742,
          "Y": 588.2409,
          "Z": -4.754745,
          "Type": "None",
          "Action": ""
        },
        {
          "X": 577.3087,
          "Y": 591.5098,
          "Z": -4.754745,
          "Type": "None",
          "Action": ""
        },
        {
          "X": 584.8184,
          "Y": 582.2494,
          "Z": -4.754745,
          "Type": "None",
          "Action": ""
        },
        {
          "X": 587.439148,
          "Y": 571.6417,
          "Z": -4.120542,
          "Type": "None",
          "Action": ""
        },
        {
          "X": 586.616333,
          "Y": 562.274963,
          "Z": -4.75473738,
          "Type": "None",
          "Action": ""
        },
        {
          "X": 586.4819,
          "Y": 549.3959,
          "Z": 2.20297766,
          "Type": "None",
          "Action": ""
        },
        {
          "X": 586.3779,
          "Y": 536.006042,
          "Z": 6.77016973,
          "Type": "None",
          "Action": ""
        },
        {
          "X": 574.3446,
          "Y": 535.916,
          "Z": 10.1845655,
          "Type": "None",
          "Action": ""
        },
        {
          "X": 561.5034,
          "Y": 535.7808,
          "Z": 17.0747833,
          "Type": "None",
          "Action": ""
        },
        {
          "X": 553.7356,
          "Y": 535.753357,
          "Z": 21.2429,
          "Type": "None",
          "Action": ""
        },
        {
          "X": 546.4574,
          "Y": 535.589844,
          "Z": 25.14822,
          "Type": "None",
          "Action": ""
        },
        {
          "X": 538.2687,
          "Y": 535.4614,
          "Z": 27.918623,
          "Type": "None",
          "Action": ""
        },
        {
          "X": 524.139648,
          "Y": 536.0148,
          "Z": 27.918623,
          "Type": "None",
          "Action": ""
        },
        {
          "X": 516.965149,
          "Y": 544.1357,
          "Z": 27.9172211,
          "Type": "None",
          "Action": ""
        },
        {
          "X": 514.782959,
          "Y": 553.9716,
          "Z": 27.9158115,
          "Type": "None",
          "Action": ""
        },
        {
          "X": 501.370422,
          "Y": 559.522461,
          "Z": 27.9128857,
          "Type": "None",
          "Action": ""
        },
        {
          "X": 491.766235,
          "Y": 557.4281,
          "Z": 27.9128857,
          "Type": "None",
          "Action": ""
        },
        {
          "X": 485.438354,
          "Y": 552.357666,
          "Z": 27.9128857,
          "Type": "None",
          "Action": ""
        },
        {
          "X": 481.532654,
          "Y": 543.6693,
          "Z": 27.9128857,
          "Type": "None",
          "Action": ""
        },
        {
          "X": 487.136322,
          "Y": 535.3122,
          "Z": 27.9129677,
          "Type": "None",
          "Action": ""
        },
        {
          "X": 490.749756,
          "Y": 527.916931,
          "Z": 27.913168,
          "Type": "None",
          "Action": ""
        },
        {
          "X": 491.048523,
          "Y": 516.2,
          "Z": 29.4634228,
          "Type": "None",
          "Action": ""
        }
      ],
      "IgnoreFightsDuringPath": false,
      "Name": "Move to gate 2",
      "CompleteCondition": {
        "ConditionType": 0,
        "ConditionTimer": null,
        "GetTimerTimeLeft": 0.0,
        "TimerTimeInSeconds": 0,
        "HaveItemId": 0,
        "HaveItemMustReturnTrue": true,
        "CanGossipMobId": 0,
        "CanGossipMustReturnTrue": true,
        "InitialFlags": 0,
        "FlagsChangedGameObjectId": 0,
        "DeadMobId": 0,
        "MobDeadMustReturnTrue": true,
        "MobAtPositionId": 0,
        "MobAtPositionVector": null,
        "MobAtPositionMustReturnTrue": true,
        "LOSPositionVectorFrom": null,
        "LOSPositionVectorTo": null,
        "LOSMustReturnTrue": true,
        "MobAttackableEntry": 0,
        "MobAttackableMustReturnTrue": false,
        "MobAttackableSkipIfAbsent": false
      },
      "StepFaction": 0,
      "HasCompleteCondition": false
    },
    {
      "$type": "WholesomeDungeonCrawler.Models.RegroupModel, WholesomeDungeonCrawler",
      "RegroupSpot": {
        "X": 491.0526,
        "Y": 517.9974,
        "Z": 29.46172,
        "Type": "None",
        "Action": ""
      },
      "Name": "Regroup before gate 2",
      "CompleteCondition": {
        "ConditionType": 0,
        "ConditionTimer": null,
        "GetTimerTimeLeft": 0.0,
        "TimerTimeInSeconds": 0,
        "HaveItemId": 0,
        "HaveItemMustReturnTrue": true,
        "CanGossipMobId": 0,
        "CanGossipMustReturnTrue": true,
        "InitialFlags": 0,
        "FlagsChangedGameObjectId": 0,
        "DeadMobId": 0,
        "MobDeadMustReturnTrue": true,
        "MobAtPositionId": 0,
        "MobAtPositionVector": null,
        "MobAtPositionMustReturnTrue": true,
        "LOSPositionVectorFrom": null,
        "LOSPositionVectorTo": null,
        "LOSMustReturnTrue": true,
        "MobAttackableEntry": 0,
        "MobAttackableMustReturnTrue": false,
        "MobAttackableSkipIfAbsent": false
      },
      "StepFaction": 0,
      "HasCompleteCondition": false
    },
    {
      "$type": "WholesomeDungeonCrawler.Models.InteractWithModel, WholesomeDungeonCrawler",
      "ObjectId": "177217",
      "ExpectedPosition": {
        "X": 491.204,
        "Y": 515.133,
        "Z": 29.4675,
        "Type": "None",
        "Action": ""
      },
      "InteractDistance": 3,
      "SkipIfNotFound": false,
      "Name": "Open gate 2",
      "CompleteCondition": {
        "ConditionType": 0,
        "ConditionTimer": null,
        "GetTimerTimeLeft": 0.0,
        "TimerTimeInSeconds": 0,
        "HaveItemId": 0,
        "HaveItemMustReturnTrue": true,
        "CanGossipMobId": 0,
        "CanGossipMustReturnTrue": true,
        "InitialFlags": 0,
        "FlagsChangedGameObjectId": 0,
        "DeadMobId": 0,
        "MobDeadMustReturnTrue": true,
        "MobAtPositionId": 0,
        "MobAtPositionVector": null,
        "MobAtPositionMustReturnTrue": true,
        "LOSPositionVectorFrom": {
          "X": 491.0485,
          "Y": 516.2,
          "Z": 29.46342,
          "Type": "None",
          "Action": ""
        },
        "LOSPositionVectorTo": {
          "X": 491.1667,
          "Y": 505.2324,
          "Z": 29.46342,
          "Type": "None",
          "Action": ""
        },
        "LOSMustReturnTrue": true,
        "MobAttackableEntry": 0,
        "MobAttackableMustReturnTrue": false,
        "MobAttackableSkipIfAbsent": false
      },
      "StepFaction": 0,
      "HasCompleteCondition": false
    },
    {
      "$type": "WholesomeDungeonCrawler.Models.DefendSpotModel, WholesomeDungeonCrawler",
      "DefendPosition": {
        "X": 491.0721,
        "Y": 520.3126,
        "Z": 29.46257,
        "Type": "None",
        "Action": ""
      },
      "Timer": 10,
      "DefendSpotRadius": 6,
      "DefendSpotZLimit": 5,
      "ResetTimerOnCombat": false,
      "Name": "Wait for the gate 2 to open",
      "CompleteCondition": {
        "ConditionType": 0,
        "ConditionTimer": null,
        "GetTimerTimeLeft": 0.0,
        "TimerTimeInSeconds": 0,
        "HaveItemId": 0,
        "HaveItemMustReturnTrue": true,
        "CanGossipMobId": 0,
        "CanGossipMustReturnTrue": true,
        "InitialFlags": 0,
        "FlagsChangedGameObjectId": 0,
        "DeadMobId": 0,
        "MobDeadMustReturnTrue": true,
        "MobAtPositionId": 0,
        "MobAtPositionVector": null,
        "MobAtPositionMustReturnTrue": true,
        "LOSPositionVectorFrom": {
          "X": 491.0721,
          "Y": 520.3126,
          "Z": 29.46257,
          "Type": "None",
          "Action": ""
        },
        "LOSPositionVectorTo": {
          "X": 491.3334,
          "Y": 505.1631,
          "Z": 29.46257,
          "Type": "None",
          "Action": ""
        },
        "LOSMustReturnTrue": true,
        "MobAttackableEntry": 0,
        "MobAttackableMustReturnTrue": false,
        "MobAttackableSkipIfAbsent": false
      },
      "StepFaction": 0,
      "HasCompleteCondition": false
    },
    {
      "$type": "WholesomeDungeonCrawler.Models.JumpToStepModel, WholesomeDungeonCrawler",
      "StepToJumpTo": "Leave dungeon",
      "Name": "If gate is still closed - proceed to leave",
      "CompleteCondition": {
        "ConditionType": 6,
        "ConditionTimer": null,
        "GetTimerTimeLeft": 0.0,
        "TimerTimeInSeconds": 0,
        "HaveItemId": 0,
        "HaveItemMustReturnTrue": true,
        "CanGossipMobId": 0,
        "CanGossipMustReturnTrue": true,
        "InitialFlags": 0,
        "FlagsChangedGameObjectId": 0,
        "DeadMobId": 0,
        "MobDeadMustReturnTrue": true,
        "MobAtPositionId": 0,
        "MobAtPositionVector": null,
        "MobAtPositionMustReturnTrue": true,
        "LOSPositionVectorFrom": {
          "X": 491.0721,
          "Y": 520.3126,
          "Z": 29.46257,
          "Type": "None",
          "Action": ""
        },
        "LOSPositionVectorTo": {
          "X": 491.416,
          "Y": 505.7411,
          "Z": 29.46257,
          "Type": "None",
          "Action": ""
        },
        "LOSMustReturnTrue": false,
        "MobAttackableEntry": 0,
        "MobAttackableMustReturnTrue": false,
        "MobAttackableSkipIfAbsent": false
      },
      "StepFaction": 0,
      "HasCompleteCondition": true
    },
    {
      "$type": "WholesomeDungeonCrawler.Models.MoveAlongPathModel, WholesomeDungeonCrawler",
      "Path": [
        {
          "X": 491.377838,
          "Y": 510.137817,
          "Z": 29.4626122,
          "Type": "None",
          "Action": ""
        },
        {
          "X": 491.56897,
          "Y": 498.939728,
          "Z": 29.4626122,
          "Type": "None",
          "Action": ""
        },
        {
          "X": 491.714935,
          "Y": 489.8098,
          "Z": 29.4626122,
          "Type": "None",
          "Action": ""
        },
        {
          "X": 496.407562,
          "Y": 481.013123,
          "Z": 29.4626122,
          "Type": "None",
          "Action": ""
        },
        {
          "X": 505.8493,
          "Y": 480.6206,
          "Z": 29.4626122,
          "Type": "None",
          "Action": ""
        },
        {
          "X": 516.7289,
          "Y": 480.876282,
          "Z": 29.4626122,
          "Type": "None",
          "Action": ""
        },
        {
          "X": 530.7539,
          "Y": 481.403442,
          "Z": 29.4626122,
          "Type": "None",
          "Action": ""
        },
        {
          "X": 540.2295,
          "Y": 481.1724,
          "Z": 29.462719,
          "Type": "None",
          "Action": ""
        },
        {
          "X": 550.2015,
          "Y": 481.024231,
          "Z": 29.462719,
          "Type": "None",
          "Action": ""
        },
        {
          "X": 559.509338,
          "Y": 481.211,
          "Z": 29.462719,
          "Type": "None",
          "Action": ""
        },
        {
          "X": 573.5414,
          "Y": 481.4834,
          "Z": 29.462719,
          "Type": "None",
          "Action": ""
        },
        {
          "X": 587.6455,
          "Y": 481.59848,
          "Z": 29.462719,
          "Type": "None",
          "Action": ""
        },
        {
          "X": 602.1003,
          "Y": 481.670441,
          "Z": 29.462719,
          "Type": "None",
          "Action": ""
        },
        {
          "X": 615.923157,
          "Y": 481.9073,
          "Z": 29.462719,
          "Type": "None",
          "Action": ""
        }
      ],
      "IgnoreFightsDuringPath": false,
      "Name": "Boss 5 - Captain Kromcrush",
      "CompleteCondition": {
        "ConditionType": 0,
        "ConditionTimer": null,
        "GetTimerTimeLeft": 0.0,
        "TimerTimeInSeconds": 0,
        "HaveItemId": 0,
        "HaveItemMustReturnTrue": true,
        "CanGossipMobId": 0,
        "CanGossipMustReturnTrue": true,
        "InitialFlags": 0,
        "FlagsChangedGameObjectId": 0,
        "DeadMobId": 0,
        "MobDeadMustReturnTrue": true,
        "MobAtPositionId": 0,
        "MobAtPositionVector": null,
        "MobAtPositionMustReturnTrue": true,
        "LOSPositionVectorFrom": null,
        "LOSPositionVectorTo": null,
        "LOSMustReturnTrue": true,
        "MobAttackableEntry": 0,
        "MobAttackableMustReturnTrue": false,
        "MobAttackableSkipIfAbsent": false
      },
      "StepFaction": 0,
      "HasCompleteCondition": false
    },
    {
      "$type": "WholesomeDungeonCrawler.Models.MoveAlongPathModel, WholesomeDungeonCrawler",
      "Path": [
        {
          "X": 623.0491,
          "Y": 482.0342,
          "Z": 29.4641743,
          "Type": "None",
          "Action": ""
        },
        {
          "X": 632.322937,
          "Y": 481.889465,
          "Z": 29.4641743,
          "Type": "None",
          "Action": ""
        },
        {
          "X": 643.084351,
          "Y": 481.720917,
          "Z": 29.4703159,
          "Type": "None",
          "Action": ""
        },
        {
          "X": 652.6396,
          "Y": 478.443939,
          "Z": 29.45648,
          "Type": "None",
          "Action": ""
        },
        {
          "X": 661.6906,
          "Y": 474.4228,
          "Z": 29.45648,
          "Type": "None",
          "Action": ""
        },
        {
          "X": 670.745361,
          "Y": 475.485046,
          "Z": 29.45648,
          "Type": "None",
          "Action": ""
        },
        {
          "X": 677.0901,
          "Y": 487.4948,
          "Z": 29.45765,
          "Type": "None",
          "Action": ""
        },
        {
          "X": 686.9195,
          "Y": 492.905182,
          "Z": 29.4647217,
          "Type": "None",
          "Action": ""
        },
        {
          "X": 694.558838,
          "Y": 497.627228,
          "Z": 28.1760616,
          "Type": "None",
          "Action": ""
        },
        {
          "X": 705.4488,
          "Y": 498.7559,
          "Z": 28.1769447,
          "Type": "None",
          "Action": ""
        },
        {
          "X": 708.7386,
          "Y": 490.8233,
          "Z": 28.1772041,
          "Type": "None",
          "Action": ""
        },
        {
          "X": 712.6243,
          "Y": 482.1345,
          "Z": 28.1776,
          "Type": "None",
          "Action": ""
        },
        {
          "X": 718.0076,
          "Y": 468.983673,
          "Z": 28.1777782,
          "Type": "None",
          "Action": ""
        },
        {
          "X": 722.0041,
          "Y": 459.464783,
          "Z": 28.1779327,
          "Type": "None",
          "Action": ""
        },
        {
          "X": 728.660339,
          "Y": 447.214539,
          "Z": 28.1784573,
          "Type": "None",
          "Action": ""
        },
        {
          "X": 737.619751,
          "Y": 435.052277,
          "Z": 28.1795158,
          "Type": "None",
          "Action": ""
        },
        {
          "X": 746.6443,
          "Y": 437.4396,
          "Z": 28.1811466,
          "Type": "None",
          "Action": ""
        },
        {
          "X": 753.778442,
          "Y": 448.9437,
          "Z": 28.1823883,
          "Type": "None",
          "Action": ""
        },
        {
          "X": 755.113647,
          "Y": 457.0108,
          "Z": 28.1823883,
          "Type": "None",
          "Action": ""
        },
        {
          "X": 755.1598,
          "Y": 467.299622,
          "Z": 28.1823883,
          "Type": "None",
          "Action": ""
        },
        {
          "X": 754.351257,
          "Y": 476.8893,
          "Z": 28.1823883,
          "Type": "None",
          "Action": ""
        },
        {
          "X": 761.7104,
          "Y": 481.849976,
          "Z": 27.7884884,
          "Type": "None",
          "Action": ""
        },
        {
          "X": 775.2419,
          "Y": 482.38205,
          "Z": 32.9418221,
          "Type": "None",
          "Action": ""
        },
        {
          "X": 784.8078,
          "Y": 475.370148,
          "Z": 36.8934555,
          "Type": "None",
          "Action": ""
        },
        {
          "X": 796.4836,
          "Y": 472.6326,
          "Z": 37.31822,
          "Type": "None",
          "Action": ""
        },
        {
          "X": 804.83905,
          "Y": 473.3276,
          "Z": 37.31822,
          "Type": "None",
          "Action": ""
        },
        {
          "X": 816.2618,
          "Y": 476.9148,
          "Z": 37.31822,
          "Type": "None",
          "Action": ""
        },
        {
          "X": 823.745056,
          "Y": 480.792023,
          "Z": 37.31822,
          "Type": "None",
          "Action": ""
        }
      ],
      "IgnoreFightsDuringPath": false,
      "Name": "Boss 6 - King Gordok",
      "CompleteCondition": {
        "ConditionType": 0,
        "ConditionTimer": null,
        "GetTimerTimeLeft": 0.0,
        "TimerTimeInSeconds": 0,
        "HaveItemId": 0,
        "HaveItemMustReturnTrue": true,
        "CanGossipMobId": 0,
        "CanGossipMustReturnTrue": true,
        "InitialFlags": 0,
        "FlagsChangedGameObjectId": 0,
        "DeadMobId": 0,
        "MobDeadMustReturnTrue": true,
        "MobAtPositionId": 0,
        "MobAtPositionVector": null,
        "MobAtPositionMustReturnTrue": true,
        "LOSPositionVectorFrom": null,
        "LOSPositionVectorTo": null,
        "LOSMustReturnTrue": true,
        "MobAttackableEntry": 0,
        "MobAttackableMustReturnTrue": false,
        "MobAttackableSkipIfAbsent": false
      },
      "StepFaction": 0,
      "HasCompleteCondition": false
    },
    {
      "$type": "WholesomeDungeonCrawler.Models.LeaveDungeonModel, WholesomeDungeonCrawler",
      "Name": "Leave dungeon",
      "CompleteCondition": {
        "ConditionType": 0,
        "ConditionTimer": null,
        "GetTimerTimeLeft": 0.0,
        "TimerTimeInSeconds": 0,
        "HaveItemId": 0,
        "HaveItemMustReturnTrue": true,
        "CanGossipMobId": 0,
        "CanGossipMustReturnTrue": true,
        "InitialFlags": 0,
        "FlagsChangedGameObjectId": 0,
        "DeadMobId": 0,
        "MobDeadMustReturnTrue": true,
        "MobAtPositionId": 0,
        "MobAtPositionVector": null,
        "MobAtPositionMustReturnTrue": true,
        "LOSPositionVectorFrom": null,
        "LOSPositionVectorTo": null,
        "LOSMustReturnTrue": true,
        "MobAttackableEntry": 0,
        "MobAttackableMustReturnTrue": false,
        "MobAttackableSkipIfAbsent": false
      },
      "StepFaction": 0,
      "HasCompleteCondition": false
    }
  ],
  "MapId": 429,
  "ProfileName": "Dire_Maul_North",
  "DungeonName": "Dire Maul North",
  "DeathRunPaths": [
    {
      "Name": "Dire_Maul_North [Converted]",
      "Path": [
        {
          "X": -4587.57568,
          "Y": 1631.13013,
          "Z": 94.01817,
          "Type": "None",
          "Action": ""
        },
        {
          "X": -4574.184,
          "Y": 1624.29333,
          "Z": 94.2845459,
          "Type": "None",
          "Action": ""
        },
        {
          "X": -4567.705,
          "Y": 1617.56055,
          "Z": 95.44248,
          "Type": "None",
          "Action": ""
        },
        {
          "X": -4563.326,
          "Y": 1609.4043,
          "Z": 97.22026,
          "Type": "None",
          "Action": ""
        },
        {
          "X": -4557.462,
          "Y": 1596.003,
          "Z": 99.80476,
          "Type": "None",
          "Action": ""
        },
        {
          "X": -4552.13672,
          "Y": 1582.97974,
          "Z": 102.13446,
          "Type": "None",
          "Action": ""
        },
        {
          "X": -4549.18066,
          "Y": 1573.55,
          "Z": 102.831657,
          "Type": "None",
          "Action": ""
        },
        {
          "X": -4546.246,
          "Y": 1559.6106,
          "Z": 102.612579,
          "Type": "None",
          "Action": ""
        },
        {
          "X": -4543.39063,
          "Y": 1545.85693,
          "Z": 103.22049,
          "Type": "None",
          "Action": ""
        },
        {
          "X": -4540.735,
          "Y": 1531.6488,
          "Z": 102.611076,
          "Type": "None",
          "Action": ""
        },
        {
          "X": -4539.02832,
          "Y": 1517.713,
          "Z": 102.792053,
          "Type": "None",
          "Action": ""
        },
        {
          "X": -4538.512,
          "Y": 1503.65381,
          "Z": 102.062477,
          "Type": "None",
          "Action": ""
        },
        {
          "X": -4538.59229,
          "Y": 1490.72437,
          "Z": 102.426659,
          "Type": "None",
          "Action": ""
        },
        {
          "X": -4538.183,
          "Y": 1476.7406,
          "Z": 103.934113,
          "Type": "None",
          "Action": ""
        },
        {
          "X": -4536.84668,
          "Y": 1462.31274,
          "Z": 106.233093,
          "Type": "None",
          "Action": ""
        },
        {
          "X": -4536.2417,
          "Y": 1448.26038,
          "Z": 108.416527,
          "Type": "None",
          "Action": ""
        },
        {
          "X": -4537.92969,
          "Y": 1434.59021,
          "Z": 109.568954,
          "Type": "None",
          "Action": ""
        },
        {
          "X": -4537.86,
          "Y": 1426.72546,
          "Z": 111.388466,
          "Type": "None",
          "Action": ""
        },
        {
          "X": -4531.042,
          "Y": 1417.84119,
          "Z": 117.016335,
          "Type": "None",
          "Action": ""
        },
        {
          "X": -4524.93262,
          "Y": 1411.25452,
          "Z": 124.854866,
          "Type": "None",
          "Action": ""
        },
        {
          "X": -4517.50732,
          "Y": 1404.91858,
          "Z": 126.867966,
          "Type": "None",
          "Action": ""
        },
        {
          "X": -4509.54834,
          "Y": 1398.85352,
          "Z": 126.071175,
          "Type": "None",
          "Action": ""
        },
        {
          "X": -4501.842,
          "Y": 1393.99512,
          "Z": 126.118004,
          "Type": "None",
          "Action": ""
        },
        {
          "X": -4494.17236,
          "Y": 1390.08118,
          "Z": 127.394318,
          "Type": "None",
          "Action": ""
        },
        {
          "X": -4484.41455,
          "Y": 1385.10144,
          "Z": 126.3774,
          "Type": "None",
          "Action": ""
        },
        {
          "X": -4477.84473,
          "Y": 1379.31726,
          "Z": 125.826622,
          "Type": "None",
          "Action": ""
        },
        {
          "X": -4476.09863,
          "Y": 1371.4967,
          "Z": 125.375717,
          "Type": "None",
          "Action": ""
        },
        {
          "X": -4472.455,
          "Y": 1357.54675,
          "Z": 125.37796,
          "Type": "None",
          "Action": ""
        },
        {
          "X": -4468.344,
          "Y": 1349.94775,
          "Z": 125.264061,
          "Type": "None",
          "Action": ""
        },
        {
          "X": -4462.20264,
          "Y": 1340.84534,
          "Z": 125.307526,
          "Type": "None",
          "Action": ""
        },
        {
          "X": -4449.759,
          "Y": 1334.98254,
          "Z": 126.002365,
          "Type": "None",
          "Action": ""
        },
        {
          "X": -4435.342,
          "Y": 1334.04089,
          "Z": 126.002365,
          "Type": "None",
          "Action": ""
        },
        {
          "X": -4421.175,
          "Y": 1333.5979,
          "Z": 132.4162,
          "Type": "None",
          "Action": ""
        },
        {
          "X": -4407.23047,
          "Y": 1332.83728,
          "Z": 138.863983,
          "Type": "None",
          "Action": ""
        },
        {
          "X": -4392.748,
          "Y": 1332.363,
          "Z": 145.687881,
          "Type": "None",
          "Action": ""
        },
        {
          "X": -4385.61133,
          "Y": 1332.1427,
          "Z": 149.380188,
          "Type": "None",
          "Action": ""
        },
        {
          "X": -4371.61865,
          "Y": 1331.74841,
          "Z": 155.648651,
          "Type": "None",
          "Action": ""
        },
        {
          "X": -4357.16748,
          "Y": 1331.42261,
          "Z": 159.233276,
          "Type": "None",
          "Action": ""
        },
        {
          "X": -4342.97754,
          "Y": 1330.94263,
          "Z": 159.233765,
          "Type": "None",
          "Action": ""
        },
        {
          "X": -4331.49854,
          "Y": 1330.77014,
          "Z": 159.233932,
          "Type": "None",
          "Action": ""
        },
        {
          "X": -4321.996,
          "Y": 1330.653,
          "Z": 159.233963,
          "Type": "None",
          "Action": ""
        },
        {
          "X": -4312.511,
          "Y": 1330.66748,
          "Z": 159.233963,
          "Type": "None",
          "Action": ""
        },
        {
          "X": -4298.5127,
          "Y": 1330.50745,
          "Z": 159.233963,
          "Type": "None",
          "Action": ""
        },
        {
          "X": -4283.91846,
          "Y": 1330.24329,
          "Z": 161.213531,
          "Type": "None",
          "Action": ""
        },
        {
          "X": -4269.97461,
          "Y": 1328.78,
          "Z": 161.213531,
          "Type": "None",
          "Action": ""
        },
        {
          "X": -4255.73828,
          "Y": 1326.08533,
          "Z": 161.213531,
          "Type": "None",
          "Action": ""
        },
        {
          "X": -4241.765,
          "Y": 1322.28259,
          "Z": 161.213531,
          "Type": "None",
          "Action": ""
        },
        {
          "X": -4227.98047,
          "Y": 1317.70544,
          "Z": 161.213531,
          "Type": "None",
          "Action": ""
        },
        {
          "X": -4214.71045,
          "Y": 1313.243,
          "Z": 161.213531,
          "Type": "None",
          "Action": ""
        },
        {
          "X": -4201.378,
          "Y": 1308.74768,
          "Z": 161.213531,
          "Type": "None",
          "Action": ""
        },
        {
          "X": -4192.53174,
          "Y": 1297.93738,
          "Z": 161.213638,
          "Type": "None",
          "Action": ""
        },
        {
          "X": -4188.54053,
          "Y": 1284.55408,
          "Z": 161.213638,
          "Type": "None",
          "Action": ""
        },
        {
          "X": -4185.865,
          "Y": 1270.314,
          "Z": 161.213638,
          "Type": "None",
          "Action": ""
        },
        {
          "X": -4183.329,
          "Y": 1256.54565,
          "Z": 161.213638,
          "Type": "None",
          "Action": ""
        },
        {
          "X": -4180.79248,
          "Y": 1242.77734,
          "Z": 161.213638,
          "Type": "None",
          "Action": ""
        },
        {
          "X": -4178.129,
          "Y": 1228.32068,
          "Z": 161.213638,
          "Type": "None",
          "Action": ""
        },
        {
          "X": -4175.586,
          "Y": 1214.518,
          "Z": 161.213638,
          "Type": "None",
          "Action": ""
        },
        {
          "X": -4173.043,
          "Y": 1200.71521,
          "Z": 161.213638,
          "Type": "None",
          "Action": ""
        },
        {
          "X": -4170.42432,
          "Y": 1186.49951,
          "Z": 161.213638,
          "Type": "None",
          "Action": ""
        },
        {
          "X": -4167.87061,
          "Y": 1172.699,
          "Z": 161.213638,
          "Type": "None",
          "Action": ""
        },
        {
          "X": -4164.75342,
          "Y": 1158.51807,
          "Z": 161.213638,
          "Type": "None",
          "Action": ""
        },
        {
          "X": -4154.896,
          "Y": 1152.38159,
          "Z": 161.213638,
          "Type": "None",
          "Action": ""
        },
        {
          "X": -4143.716,
          "Y": 1147.74329,
          "Z": 161.213638,
          "Type": "None",
          "Action": ""
        },
        {
          "X": -4130.615,
          "Y": 1142.62134,
          "Z": 161.213638,
          "Type": "None",
          "Action": ""
        },
        {
          "X": -4116.747,
          "Y": 1138.75647,
          "Z": 161.213638,
          "Type": "None",
          "Action": ""
        },
        {
          "X": -4102.658,
          "Y": 1137.00549,
          "Z": 161.213638,
          "Type": "None",
          "Action": ""
        },
        {
          "X": -4093.29,
          "Y": 1136.54224,
          "Z": 161.213638,
          "Type": "None",
          "Action": ""
        },
        {
          "X": -4083.53516,
          "Y": 1136.097,
          "Z": 161.213638,
          "Type": "None",
          "Action": ""
        },
        {
          "X": -4070.76782,
          "Y": 1135.69763,
          "Z": 161.213638,
          "Type": "None",
          "Action": ""
        },
        {
          "X": -4059.6853,
          "Y": 1144.97791,
          "Z": 161.213638,
          "Type": "None",
          "Action": ""
        },
        {
          "X": -4048.857,
          "Y": 1154.0708,
          "Z": 159.781433,
          "Type": "None",
          "Action": ""
        },
        {
          "X": -4038.43359,
          "Y": 1164.064,
          "Z": 159.742111,
          "Type": "None",
          "Action": ""
        },
        {
          "X": -4032.659,
          "Y": 1172.93042,
          "Z": 159.718018,
          "Type": "None",
          "Action": ""
        },
        {
          "X": -4027.896,
          "Y": 1182.40564,
          "Z": 159.6985,
          "Type": "None",
          "Action": ""
        },
        {
          "X": -4021.14673,
          "Y": 1195.2124,
          "Z": 159.6673,
          "Type": "None",
          "Action": ""
        },
        {
          "X": -4014.01953,
          "Y": 1199.88965,
          "Z": 161.09079,
          "Type": "None",
          "Action": ""
        },
        {
          "X": -3999.601,
          "Y": 1200.05371,
          "Z": 161.08139,
          "Type": "None",
          "Action": ""
        },
        {
          "X": -3991.17578,
          "Y": 1199.65662,
          "Z": 161.059219,
          "Type": "None",
          "Action": ""
        },
        {
          "X": -3982.33984,
          "Y": 1196.28625,
          "Z": 161.046768,
          "Type": "None",
          "Action": ""
        },
        {
          "X": -3982.07617,
          "Y": 1184.80591,
          "Z": 161.043457,
          "Type": "None",
          "Action": ""
        },
        {
          "X": -3982.303,
          "Y": 1170.77271,
          "Z": 161.032654,
          "Type": "None",
          "Action": ""
        },
        {
          "X": -3982.278,
          "Y": 1156.2832,
          "Z": 161.027618,
          "Type": "None",
          "Action": ""
        },
        {
          "X": -3982.06055,
          "Y": 1144.94751,
          "Z": 161.013947,
          "Type": "None",
          "Action": ""
        },
        {
          "X": -3975.02832,
          "Y": 1140.6145,
          "Z": 161.011063,
          "Type": "None",
          "Action": ""
        },
        {
          "X": -3962.69385,
          "Y": 1134.075,
          "Z": 161.046219,
          "Type": "None",
          "Action": ""
        },
        {
          "X": -3953.49951,
          "Y": 1132.951,
          "Z": 158.372787,
          "Type": "None",
          "Action": ""
        },
        {
          "X": -3939.49829,
          "Y": 1133.64319,
          "Z": 151.397156,
          "Type": "None",
          "Action": ""
        },
        {
          "X": -3925.04248,
          "Y": 1134.63025,
          "Z": 148.7512,
          "Type": "None",
          "Action": ""
        },
        {
          "X": -3911.1145,
          "Y": 1136.04419,
          "Z": 149.186066,
          "Type": "None",
          "Action": ""
        },
        {
          "X": -3897.15112,
          "Y": 1137.77344,
          "Z": 151.1664,
          "Type": "None",
          "Action": ""
        },
        {
          "X": -3882.771,
          "Y": 1139.55432,
          "Z": 154.451126,
          "Type": "None",
          "Action": ""
        },
        {
          "X": -3868.84253,
          "Y": 1141.2793,
          "Z": 154.788467,
          "Type": "None",
          "Action": ""
        },
        {
          "X": -3854.497,
          "Y": 1143.05591,
          "Z": 154.788467,
          "Type": "None",
          "Action": ""
        },
        {
          "X": -3840.61,
          "Y": 1144.82922,
          "Z": 154.788467,
          "Type": "None",
          "Action": ""
        },
        {
          "X": -3826.69873,
          "Y": 1146.90173,
          "Z": 154.788467,
          "Type": "None",
          "Action": ""
        },
        {
          "X": -3812.7915,
          "Y": 1151.54749,
          "Z": 154.788467,
          "Type": "None",
          "Action": ""
        },
        {
          "X": -3803.443,
          "Y": 1155.00745,
          "Z": 154.788467,
          "Type": "None",
          "Action": ""
        },
        {
          "X": -3790.35181,
          "Y": 1161.2821,
          "Z": 154.788467,
          "Type": "None",
          "Action": ""
        },
        {
          "X": -3778.366,
          "Y": 1168.51636,
          "Z": 154.788467,
          "Type": "None",
          "Action": ""
        },
        {
          "X": -3764.70215,
          "Y": 1172.69873,
          "Z": 154.786911,
          "Type": "None",
          "Action": ""
        },
        {
          "X": -3755.895,
          "Y": 1171.78784,
          "Z": 154.786911,
          "Type": "None",
          "Action": ""
        },
        {
          "X": -3742.023,
          "Y": 1169.45862,
          "Z": 154.786911,
          "Type": "None",
          "Action": ""
        },
        {
          "X": -3728.42529,
          "Y": 1164.469,
          "Z": 154.787186,
          "Type": "None",
          "Action": ""
        },
        {
          "X": -3715.356,
          "Y": 1159.25757,
          "Z": 154.787231,
          "Type": "None",
          "Action": ""
        },
        {
          "X": -3701.83154,
          "Y": 1153.86462,
          "Z": 154.787231,
          "Type": "None",
          "Action": ""
        },
        {
          "X": -3688.549,
          "Y": 1149.49182,
          "Z": 154.787231,
          "Type": "None",
          "Action": ""
        },
        {
          "X": -3674.70215,
          "Y": 1147.02063,
          "Z": 154.787231,
          "Type": "None",
          "Action": ""
        },
        {
          "X": -3660.396,
          "Y": 1144.71875,
          "Z": 154.787231,
          "Type": "None",
          "Action": ""
        },
        {
          "X": -3646.53931,
          "Y": 1142.48926,
          "Z": 154.787231,
          "Type": "None",
          "Action": ""
        },
        {
          "X": -3632.26782,
          "Y": 1140.193,
          "Z": 154.787231,
          "Type": "None",
          "Action": ""
        },
        {
          "X": -3618.37646,
          "Y": 1137.95789,
          "Z": 153.6253,
          "Type": "None",
          "Action": ""
        },
        {
          "X": -3604.51978,
          "Y": 1135.72827,
          "Z": 150.451172,
          "Type": "None",
          "Action": ""
        },
        {
          "X": -3590.21362,
          "Y": 1133.42651,
          "Z": 148.423645,
          "Type": "None",
          "Action": ""
        },
        {
          "X": -3576.32251,
          "Y": 1131.19128,
          "Z": 148.730972,
          "Type": "None",
          "Action": ""
        },
        {
          "X": -3562.50024,
          "Y": 1128.96741,
          "Z": 152.850922,
          "Type": "None",
          "Action": ""
        },
        {
          "X": -3555.209,
          "Y": 1127.79419,
          "Z": 156.478058,
          "Type": "None",
          "Action": ""
        },
        {
          "X": -3541.31763,
          "Y": 1125.55908,
          "Z": 161.028046,
          "Type": "None",
          "Action": ""
        },
        {
          "X": -3531.82813,
          "Y": 1121.98486,
          "Z": 161.0241,
          "Type": "None",
          "Action": ""
        },
        {
          "X": -3522.485,
          "Y": 1115.021,
          "Z": 161.0247,
          "Type": "None",
          "Action": ""
        },
        {
          "X": -3520.30518,
          "Y": 1106.43933,
          "Z": 161.026047,
          "Type": "None",
          "Action": ""
        },
        {
          "X": -3520.37,
          "Y": 1097.178,
          "Z": 161.026108,
          "Type": "None",
          "Action": ""
        },
        {
          "X": -3520.43555,
          "Y": 1088.75269,
          "Z": 161.071915,
          "Type": "None",
          "Action": ""
        },
        {
          "X": -3520.58936,
          "Y": 1076.08447,
          "Z": 161.15477,
          "Type": "None",
          "Action": ""
        }
      ]
    }
  ],
  "OffMeshConnections": [],
  "DungeonModel": null,
  "DeathRunPath": null
}